filedb.py
setup.py
micropython_filedb.egg-info/PKG-INFO
micropython_filedb.egg-info/SOURCES.txt
micropython_filedb.egg-info/dependency_links.txt
micropython_filedb.egg-info/top_level.txt