Metadata-Version: 1.0
Name: micropython-filedb
Version: 0.2
Summary: Very simple, filesystem-based ORM (Object-Relational
